[
  {
    "type": "file",
    "name": "about.md"
  },
  {
    "type": "file",
    "name": "1728839357174.md"
  },
  {
    "type": "file",
    "name": "1728839348479.md"
  },
  {
    "type": "file",
    "name": "13_10_2024_4.md"
  },
  {
    "type": "file",
    "name": "_info.json"
  },
  {
    "type": "file",
    "name": "contact.md"
  },
  {
    "type": "directory",
    "name": "portfolio",
    "children": [
      {
        "type": "file",
        "name": "1728839113961.md"
      },
      {
        "type": "file",
        "name": "1728839120512.md"
      },
      {
        "type": "file",
        "name": "1728839126238.md"
      },
      {
        "type": "file",
        "name": "1728839267337.md"
      },
      {
        "type": "file",
        "name": "1728839360856.md"
      },
      {
        "type": "file",
        "name": "_dir.md"
      },
      {
        "type": "file",
        "name": "espacohimalaya.md"
      },
      {
        "type": "file",
        "name": "novagokula.md"
      },
      {
        "type": "file",
        "name": "oxidereport.md"
      },
      {
        "type": "file",
        "name": "paravyomayoga.md"
      }
    ]
  },
  {
    "type": "file",
    "name": "files-order.json"
  },
  {
    "type": "directory",
    "name": "solucoes",
    "children": [
      {
        "type": "file",
        "name": "_dir.md"
      },
      {
        "type": "file",
        "name": "desenv.md"
      },
      {
        "type": "file",
        "name": "seguranca.md"
      },
      {
        "type": "file",
        "name": "siriusstudio.md"
      },
      {
        "type": "file",
        "name": "webmarketing.md"
      }
    ]
  },
  {
    "type": "file",
    "name": "teste.md"
  },
  {
    "type": "file",
    "name": "types.json"
  }
]